MANIFEST.in
setup.py
fxsim/EURUSD.csv
fxsim/__init__.py
fxsim/indicators.py
fxsim/optimizer.py
fxsim/simulator.py
fxsim.egg-info/PKG-INFO
fxsim.egg-info/SOURCES.txt
fxsim.egg-info/dependency_links.txt
fxsim.egg-info/top_level.txt