Metadata-Version: 1.1
Name: fxsim
Version: 0.0.24
Summary: Simulador de operacion en mercado forex
Home-page: http://www.alejandrocuartas.com/
Author: Alejandro Cuartas
Author-email: alejandro.cuartas@yahoo.com
License: MIT
Platform: UNKNOWN
Classifier: Programming Language :: Python :: 3
Classifier: License :: OSI Approved :: MIT License
